oll_sc/__init__.py
oll_sc/api.py
oll_sc/cli.py
oll_sc/exceptions.py
oll_sc/yk_api.py
oll_sc/opensc/opensc-pkcs11-Darwin-64bit.so
oll_sc/opensc/opensc-pkcs11-Linux-64bit.so
oll_sc/opensc/opensc-pkcs11-Windows-32bit.dll
oll_sc/opensc/opensc-pkcs11-Windows-64bit.dll
oll_sc-0.1.3.data/data/lib/site-packages/oll_sc/LICENSE.txt
oll_sc-0.1.3.data/data/lib/site-packages/oll_sc/README.md
tests/__init__.py
tests/conftest.py
tests/pkcs11.py
tests/settings.py
tests/test_api.py
oll_sc-0.1.3.dist-info/LICENSE.txt
oll_sc-0.1.3.dist-info/METADATA
oll_sc-0.1.3.dist-info/WHEEL
oll_sc-0.1.3.dist-info/entry_points.txt
oll_sc-0.1.3.dist-info/top_level.txt
oll_sc-0.1.3.dist-info/RECORD
